starling_sim/__init__.py
starling_sim/__main__.py
starling_sim/cli.py
starling_sim/model_simulator.py
starling_sim/run.py
starling_sim/simulation_scenario.py
starling_sim/version.py
starling_sim/basemodel/__init__.py
starling_sim/basemodel/simulation_model.py
starling_sim/basemodel/agent/__init__.py
starling_sim/basemodel/agent/agent.py
starling_sim/basemodel/agent/moving_agent.py
starling_sim/basemodel/agent/requests.py
starling_sim/basemodel/agent/spatial_agent.py
starling_sim/basemodel/agent/operators/__init__.py
starling_sim/basemodel/agent/operators/operator.py
starling_sim/basemodel/agent/operators/public_transport_operator.py
starling_sim/basemodel/agent/operators/station_based_operator.py
starling_sim/basemodel/agent/persons/__init__.py
starling_sim/basemodel/agent/persons/person.py
starling_sim/basemodel/agent/stations/__init__.py
starling_sim/basemodel/agent/stations/station.py
starling_sim/basemodel/agent/stations/vehicle_sharing_station.py
starling_sim/basemodel/agent/vehicles/__init__.py
starling_sim/basemodel/agent/vehicles/public_transport_vehicle.py
starling_sim/basemodel/agent/vehicles/repositioning_vehicle.py
starling_sim/basemodel/agent/vehicles/service_vehicle.py
starling_sim/basemodel/agent/vehicles/station_based_vehicle.py
starling_sim/basemodel/agent/vehicles/vehicle.py
starling_sim/basemodel/algorithms/__init__.py
starling_sim/basemodel/algorithms/algorithm.py
starling_sim/basemodel/algorithms/dispatcher.py
starling_sim/basemodel/algorithms/pal_zhang_GCH.py
starling_sim/basemodel/algorithms/pal_zhang_dispatcher.py
starling_sim/basemodel/environment/__init__.py
starling_sim/basemodel/environment/environment.py
starling_sim/basemodel/input/__init__.py
starling_sim/basemodel/input/dynamic_input.py
starling_sim/basemodel/output/__init__.py
starling_sim/basemodel/output/feature_factory.py
starling_sim/basemodel/output/geojson_output.py
starling_sim/basemodel/output/information_factory.py
starling_sim/basemodel/output/kpi_output.py
starling_sim-1.2.3.dist-info/licenses/LICENSE.txt
starling_sim-1.2.3.dist-info/METADATA
starling_sim-1.2.3.dist-info/WHEEL
starling_sim-1.2.3.dist-info/entry_points.txt
starling_sim-1.2.3.dist-info/top_level.txt
starling_sim-1.2.3.dist-info/RECORD
