Metadata-Version: 2.4
Name: starling-sim
Version: 1.2.3
Summary: Agent-based framework for mobility simulation
Home-page: https://github.com/tellae/starling
Author: Tellae
Author-email: starling@tellae.fr
License: CECILL-B
Classifier: Development Status :: 3 - Alpha
Classifier: Intended Audience :: Science/Research
Classifier: Intended Audience :: Developers
Classifier: Topic :: Scientific/Engineering :: Artificial Intelligence
Classifier: Topic :: Scientific/Engineering :: GIS
Classifier: Programming Language :: Python :: 3 :: Only
Classifier: Programming Language :: Python :: 3.9
Classifier: Programming Language :: Python :: 3.10
Classifier: Programming Language :: Python :: 3.11
Classifier: License :: CeCILL-B Free Software License Agreement (CECILL-B)
Requires-Python: >=3.9
License-File: LICENSE.txt
Requires-Dist: numpy>=1.26.0
Requires-Dist: rtree>=1.1.0
Requires-Dist: geopandas>=0.14.1
Requires-Dist: pandas>=2.1.0
Requires-Dist: shapely>=2.0.0
Requires-Dist: scipy>=1.11.0
Requires-Dist: pyproj>=3.6.0
Requires-Dist: geopy>=2.4.0
Requires-Dist: geojson>=3.1.0
Requires-Dist: jsonschema>=4.20.0
Requires-Dist: scikit-learn>=1.3.0
Requires-Dist: simpy>=4.1.0
Requires-Dist: networkx>=3.2.0
Requires-Dist: osmnx~=1.7.0
Requires-Dist: gtfs-kit>=6.0.0
Requires-Dist: mpu>=0.23.0
Requires-Dist: alns>=6.0.0
Requires-Dist: numba>=0.58.0
Requires-Dist: loguru~=0.7.3
Dynamic: author
Dynamic: author-email
Dynamic: classifier
Dynamic: description
Dynamic: description-content-type
Dynamic: home-page
Dynamic: license
Dynamic: license-file
Dynamic: requires-dist
Dynamic: requires-python
Dynamic: summary
